manticore/__init__.py
manticore/__main__.py
manticore/exceptions.py
manticore/binary/__init__.py
manticore/binary/binary.py
manticore/core/__init__.py
manticore/core/manticore.py
manticore/core/plugin.py
manticore/core/state.py
manticore/core/state_pb2.py
manticore/core/worker.py
manticore/core/workspace.py
manticore/core/parser/__init__.py
manticore/core/parser/parser.py
manticore/core/smtlib/__init__.py
manticore/core/smtlib/constraints.py
manticore/core/smtlib/expression.py
manticore/core/smtlib/operators.py
manticore/core/smtlib/solver.py
manticore/core/smtlib/visitors.py
manticore/ethereum/__init__.py
manticore/ethereum/abi.py
manticore/ethereum/abitypes.py
manticore/ethereum/account.py
manticore/ethereum/cli.py
manticore/ethereum/detectors.py
manticore/ethereum/manticore.py
manticore/ethereum/parsetab.py
manticore/ethereum/plugins.py
manticore/ethereum/solidity.py
manticore/ethereum/state.py
manticore/ethereum/verifier.py
manticore/native/__init__.py
manticore/native/cli.py
manticore/native/manticore.py
manticore/native/mappings.py
manticore/native/memory.py
manticore/native/models.py
manticore/native/plugins.py
manticore/native/state.py
manticore/native/state_merging.py
manticore/native/cpu/__init__.py
manticore/native/cpu/aarch64.py
manticore/native/cpu/abstractcpu.py
manticore/native/cpu/arm.py
manticore/native/cpu/bitwise.py
manticore/native/cpu/cpufactory.py
manticore/native/cpu/disasm.py
manticore/native/cpu/register.py
manticore/native/cpu/x86.py
manticore/platforms/__init__.py
manticore/platforms/cgcrandom.py
manticore/platforms/decree.py
manticore/platforms/evm.py
manticore/platforms/linux.py
manticore/platforms/linux_syscall_stubs.py
manticore/platforms/linux_syscalls.py
manticore/platforms/platform.py
manticore/platforms/wasm.py
manticore/utils/__init__.py
manticore/utils/command_line.py
manticore/utils/config.py
manticore/utils/deprecated.py
manticore/utils/emulate.py
manticore/utils/enums.py
manticore/utils/event.py
manticore-0.3.7.dist-info/LICENSE
manticore-0.3.7.dist-info/METADATA
manticore-0.3.7.dist-info/WHEEL
manticore-0.3.7.dist-info/entry_points.txt
manticore-0.3.7.dist-info/top_level.txt
manticore-0.3.7.dist-info/RECORD
