Metadata-Version: 2.1
Name: manticore
Version: 0.3.7
Summary: Manticore is a symbolic execution tool for analysis of binaries and smart contracts.
Home-page: https://github.com/trailofbits/manticore
Author: Trail of Bits
License: UNKNOWN
Platform: UNKNOWN
Classifier: License :: OSI Approved :: GNU Affero General Public License v3
Requires-Python: >=3.7
Provides-Extra: native
Provides-Extra: dev-noks
Provides-Extra: dev
Provides-Extra: redis
Provides-Extra: lint
